django_fluo_logs-0.2.4.dist-info/DESCRIPTION.rst
django_fluo_logs-0.2.4.dist-info/METADATA
django_fluo_logs-0.2.4.dist-info/RECORD
django_fluo_logs-0.2.4.dist-info/WHEEL
django_fluo_logs-0.2.4.dist-info/metadata.json
django_fluo_logs-0.2.4.dist-info/top_level.txt
logs/__init__.py
logs/admin.py
logs/apps.py
logs/models.py
logs/version.py
logs/migrations/0001_initial.py
logs/migrations/0002_added_realm.py
logs/migrations/__init__.py
