Metadata-Version: 2.0
Name: django-fluo-logs
Version: 0.2.4
Summary: Store Logs on DB
Home-page: https://bitbucket.org/rsalmaso/django-fluo-logs
Author: Raffaele Salmaso
Author-email: raffaele@salmaso.org
License: MIT
Platform: UNKNOWN
Classifier: Development Status :: 5 - Production/Stable
Classifier: Intended Audience :: Developers
Classifier: Natural Language :: English
Classifier: License :: OSI Approved :: MIT License
Classifier: Programming Language :: Python
Classifier: Programming Language :: Python :: 2
Classifier: Programming Language :: Python :: 2.7
Classifier: Programming Language :: Python :: 3
Classifier: Programming Language :: Python :: 3.2
Classifier: Programming Language :: Python :: 3.3
Classifier: Programming Language :: Python :: 3.4
Requires-Dist: django-fluo
